LICENSE
README.md
setup.py
kilograms/__init__.py
kilograms/histogramming.py
kilograms.egg-info/PKG-INFO
kilograms.egg-info/SOURCES.txt
kilograms.egg-info/dependency_links.txt
kilograms.egg-info/requires.txt
kilograms.egg-info/top_level.txt